{
  "link": "https://www.tripadvisor.com/Restaurants-g3311193-Binh_Duong_Province.html",
  "total_pages": 4,
  "current_page": 1,
  "total_items_count": 104,
  "items_count": 30,
  "results": [
    {
      "id": 27929294,
      "name": "King's Grill",
      "link": "https://www.tripadvisor.com/Restaurant_Review-g3311194-d27929294-Reviews-King_s_Grill-Thu_Dau_Mot_Binh_Duong_Province.html",
      "reviews": 12,
      "rating": 5,
      "price_range_usd": "$$ - $$$",
      "is_sponsored": false,
      "menu_link": null,
      "reservation_link": null,
      "featured_image": "https://dynamic-media-cdn.tripadvisor.com/media/photo-o/2c/8a/d9/e4/caption.jpg",
      "latitude": 10.976233,
      "longitude": 106.6647,
      "has_delivery": false,
      "is_premium": false,
      "cuisines": [
        "Barbecue",
        "Vietnamese"
      ]
    },
    {
      "id": 33063127,
      "name": "Hum's Pizza",
      "link": "https://www.tripadvisor.com/Restaurant_Review-g3311194-d33063127-Reviews-Hum_s_Pizza-Thu_Dau_Mot_Binh_Duong_Province.html",
      "reviews": 25,
      "rating": 5,
      "price_range_usd": null,
      "is_sponsored": false,
      "menu_link": null,
      "reservation_link": null,
      "featured_image": "https://dynamic-media-cdn.tripadvisor.com/media/photo-o/2f/92/c2/9f/check-in-t-i-nha-hang.jpg",
      "latitude": 10.973325,
      "longitude": 106.66399,
      "has_delivery": false,
      "is_premium": false,
      "cuisines": [
        "Pizza"
      ]
    },
    {
      "id": 23488850,
      "name": "Oryzaa Restaurant",
      "link": "https://www.tripadvisor.com/Restaurant_Review-g11981259-d23488850-Reviews-Oryzaa_Restaurant-Thuan_An_Binh_Duong_Province.html",
      "reviews": 24,
      "rating": 5,
      "price_range_usd": "$$ - $$$",
      "is_sponsored": false,
      "menu_link": null,
      "reservation_link": null,
      "featured_image": "https://dynamic-media-cdn.tripadvisor.com/media/photo-o/1d/40/2c/ab/oryzaa.jpg",
      "latitude": 10.923946,
      "longitude": 106.71792,
      "has_delivery": false,
      "is_premium": false,
      "cuisines": [
        "European",
        "Asian",
        "Vietnamese",
        "Diner",
        "Wine Bar"
      ]
    },
    {
      "id": 13163038,
      "name": "Akataiyo",
      "link": "https://www.tripadvisor.com/Restaurant_Review-g3311194-d13163038-Reviews-Akataiyo-Thu_Dau_Mot_Binh_Duong_Province.html",
      "reviews": 10,
      "rating": 4.5,
      "price_range_usd": "$$ - $$$",
      "is_sponsored": false,
      "menu_link": null,
      "reservation_link": null,
      "featured_image": "https://dynamic-media-cdn.tripadvisor.com/media/photo-o/11/4b/d3/bc/getlstd-property-photo.jpg",
      "latitude": 10.976695,
      "longitude": 106.670334,
      "has_delivery": false,
      "is_premium": false,
      "cuisines": [
        "Japanese",
        "Sushi"
      ]
    },
    {
      "id": 25614750,
      "name": "MION Modern Thai",
      "link": "https://www.tripadvisor.com/Restaurant_Review-g3311194-d25614750-Reviews-MION_Modern_Thai-Thu_Dau_Mot_Binh_Duong_Province.html",
      "reviews": 7,
      "rating": 5,
      "price_range_usd": null,
      "is_sponsored": false,
      "menu_link": null,
      "reservation_link": null,
      "featured_image": "https://dynamic-media-cdn.tripadvisor.com/media/photo-o/29/6b/32/a6/caption.jpg",
      "latitude": 10.974729,
      "longitude": 106.67512,
      "has_delivery": false,
      "is_premium": false,
      "cuisines": [
        "Asian",
        "Thai",
        "Vietnamese"
      ]
    },
    {
      "id": 5828083,
      "name": "Juugoya Geihinkan",
      "link": "https://www.tripadvisor.com/Restaurant_Review-g3311194-d5828083-Reviews-Juugoya_Geihinkan-Thu_Dau_Mot_Binh_Duong_Province.html",
      "reviews": 11,
      "rating": 4.5,
      "price_range_usd": "$$ - $$$",
      "is_sponsored": false,
      "menu_link": null,
      "reservation_link": null,
      "featured_image": "https://dynamic-media-cdn.tripadvisor.com/media/photo-o/05/a5/b8/77/juugoya-geihinkan.jpg",
      "latitude": 11.052378,
      "longitude": 106.67671,
      "has_delivery": false,
      "is_premium": false,
      "cuisines": [
        "Japanese",
        "Barbecue",
        "Sushi"
      ]
    },
    {
      "id": 7753779,
      "name": "An Tuong Cafe",
      "link": "https://www.tripadvisor.com/Restaurant_Review-g3311194-d7753779-Reviews-An_Tuong_Cafe-Thu_Dau_Mot_Binh_Duong_Province.html",
      "reviews": 24,
      "rating": 4.3,
      "price_range_usd": "$$ - $$$",
      "is_sponsored": false,
      "menu_link": null,
      "reservation_link": null,
      "featured_image": "https://dynamic-media-cdn.tripadvisor.com/media/photo-o/0e/f9/59/38/garden-5.jpg",
      "latitude": 10.980204,
      "longitude": 106.67057,
      "has_delivery": false,
      "is_premium": false,
      "cuisines": [
        "Italian",
        "Pizza",
        "Cafe",
        "European",
        "Vietnamese"
      ]
    },
    {
      "id": 11953821,
      "name": "The Sushi Bar 7",
      "link": "https://www.tripadvisor.com/Restaurant_Review-g3311194-d11953821-Reviews-The_Sushi_Bar_7-Thu_Dau_Mot_Binh_Duong_Province.html",
      "reviews": 12,
      "rating": 4.5,
      "price_range_usd": "$$ - $$$",
      "is_sponsored": false,
      "menu_link": null,
      "reservation_link": null,
      "featured_image": "https://dynamic-media-cdn.tripadvisor.com/media/photo-o/1a/c1/da/76/interior.jpg",
      "latitude": 11.058884,
      "longitude": 106.68353,
      "has_delivery": false,
      "is_premium": false,
      "cuisines": [
        "Japanese",
        "Seafood",
        "Sushi",
        "Asian",
        "Healthy"
      ]
    },
    {
      "id": 6437478,
      "name": "Marukame Udon",
      "link": "https://www.tripadvisor.com/Restaurant_Review-g11981259-d6437478-Reviews-Marukame_Udon-Thuan_An_Binh_Duong_Province.html",
      "reviews": 153,
      "rating": 3.9,
      "price_range_usd": "$$ - $$$",
      "is_sponsored": false,
      "menu_link": null,
      "reservation_link": null,
      "featured_image": "https://dynamic-media-cdn.tripadvisor.com/media/photo-o/0d/4f/db/25/caption.jpg",
      "latitude": 10.801348,
      "longitude": 106.61786,
      "has_delivery": false,
      "is_premium": false,
      "cuisines": [
        "Japanese",
        "Asian"
      ]
    },
    {
      "id": 25467780,
      "name": "Hideout - Kitchen & Bar",
      "link": "https://www.tripadvisor.com/Restaurant_Review-g3311194-d25467780-Reviews-Hideout_Kitchen_Bar-Thu_Dau_Mot_Binh_Duong_Province.html",
      "reviews": 3,
      "rating": 5,
      "price_range_usd": "$$ - $$$",
      "is_sponsored": false,
      "menu_link": null,
      "reservation_link": null,
      "featured_image": "https://dynamic-media-cdn.tripadvisor.com/media/photo-o/29/e7/ed/55/dining-area.jpg",
      "latitude": 10.972408,
      "longitude": 106.667244,
      "has_delivery": false,
      "is_premium": false,
      "cuisines": [
        "Vietnamese",
        "Diner",
        "Dining bars"
      ]
    },
    {
      "id": 19728550,
      "name": "Cua Ngon Binh Duong",
      "link": "https://www.tripadvisor.com/Restaurant_Review-g3311194-d19728550-Reviews-Cua_Ngon_Binh_Duong-Thu_Dau_Mot_Binh_Duong_Province.html",
      "reviews": 2,
      "rating": 5,
      "price_range_usd": "$$ - $$$",
      "is_sponsored": false,
      "menu_link": null,
      "reservation_link": null,
      "featured_image": "https://dynamic-media-cdn.tripadvisor.com/media/photo-o/1a/51/4d/8b/getlstd-property-photo.jpg",
      "latitude": 10.972603,
      "longitude": 106.666245,
      "has_delivery": false,
      "is_premium": false,
      "cuisines": [
        "Chinese",
        "Brew Pub",
        "Seafood",
        "Asian",
        "Deli",
        "Pub",
        "Vietnamese",
        "Taiwanese",
        "Singaporean",
        "Beijing cuisine"
      ]
    },
    {
      "id": 24993627,
      "name": "Pizza 4P's Hikari Bình Dương",
      "link": "https://www.tripadvisor.com/Restaurant_Review-g3311194-d24993627-Reviews-Pizza_4P_s_Hikari_Binh_Duong-Thu_Dau_Mot_Binh_Duong_Province.html",
      "reviews": 3,
      "rating": 4.7,
      "price_range_usd": "$$ - $$$",
      "is_sponsored": false,
      "menu_link": null,
      "reservation_link": null,
      "featured_image": "https://dynamic-media-cdn.tripadvisor.com/media/photo-o/2a/a7/80/99/caption.jpg",
      "latitude": 11.17141,
      "longitude": 106.77148,
      "has_delivery": false,
      "is_premium": false,
      "cuisines": [
        "Italian",
        "Japanese"
      ]
    },
    {
      "id": 14789536,
      "name": "Quan Ong Tay",
      "link": "https://www.tripadvisor.com/Restaurant_Review-g3311194-d14789536-Reviews-Quan_Ong_Tay-Thu_Dau_Mot_Binh_Duong_Province.html",
      "reviews": 12,
      "rating": 4.1,
      "price_range_usd": null,
      "is_sponsored": false,
      "menu_link": null,
      "reservation_link": null,
      "featured_image": "https://dynamic-media-cdn.tripadvisor.com/media/photo-o/13/93/67/1c/binh-duong-province.jpg",
      "latitude": 10.96896,
      "longitude": 106.65081,
      "has_delivery": false,
      "is_premium": false,
      "cuisines": [
        "Steakhouse"
      ]
    },
    {
      "id": 23992703,
      "name": "29 Eatery & Bar",
      "link": "https://www.tripadvisor.com/Restaurant_Review-g3311194-d23992703-Reviews-29_Eatery_Bar-Thu_Dau_Mot_Binh_Duong_Province.html",
      "reviews": 7,
      "rating": 5,
      "price_range_usd": null,
      "is_sponsored": false,
      "menu_link": null,
      "reservation_link": null,
      "featured_image": "https://dynamic-media-cdn.tripadvisor.com/media/photo-o/25/a6/67/43/welcome-everyone.jpg",
      "latitude": 10.972649,
      "longitude": 106.66374,
      "has_delivery": false,
      "is_premium": false,
      "cuisines": [
        "Pizza",
        "Sushi",
        "European",
        "Dining bars"
      ]
    },
    {
      "id": 10697813,
      "name": "Al Fresco's Binh Duong",
      "link": "https://www.tripadvisor.com/Restaurant_Review-g3311194-d10697813-Reviews-Al_Fresco_s_Binh_Duong-Thu_Dau_Mot_Binh_Duong_Province.html",
      "reviews": 12,
      "rating": 4.7,
      "price_range_usd": "$$ - $$$",
      "is_sponsored": false,
      "menu_link": null,
      "reservation_link": null,
      "featured_image": "https://dynamic-media-cdn.tripadvisor.com/media/photo-o/1a/49/b1/9f/quan-d-p-khong-gian-thoang.jpg",
      "latitude": 10.932089,
      "longitude": 106.71136,
      "has_delivery": false,
      "is_premium": false,
      "cuisines": [
        "American",
        "Steakhouse",
        "Pizza",
        "Cafe",
        "Barbecue",
        "Vietnamese"
      ]
    },
    {
      "id": 15009459,
      "name": "Pho Nuong Tokyo BBQ & Beer Chanh Nghia",
      "link": "https://www.tripadvisor.com/Restaurant_Review-g3311194-d15009459-Reviews-Pho_Nuong_Tokyo_BBQ_Beer_Chanh_Nghia-Thu_Dau_Mot_Binh_Duong_Province.html",
      "reviews": 4,
      "rating": 4.5,
      "price_range_usd": "$$ - $$$",
      "is_sponsored": false,
      "menu_link": null,
      "reservation_link": null,
      "featured_image": "https://dynamic-media-cdn.tripadvisor.com/media/photo-o/1b/1f/8e/a1/photo5jpg.jpg",
      "latitude": 10.973883,
      "longitude": 106.66541,
      "has_delivery": false,
      "is_premium": false,
      "cuisines": [
        "Japanese",
        "Asian",
        "Korean",
        "Vietnamese"
      ]
    },
    {
      "id": 4793470,
      "name": "Quan Vit CU CHI",
      "link": "https://www.tripadvisor.com/Restaurant_Review-g3311194-d4793470-Reviews-Quan_Vit_CU_CHI-Thu_Dau_Mot_Binh_Duong_Province.html",
      "reviews": 16,
      "rating": 4.3,
      "price_range_usd": "$$ - $$$",
      "is_sponsored": false,
      "menu_link": null,
      "reservation_link": null,
      "featured_image": "https://dynamic-media-cdn.tripadvisor.com/media/photo-o/04/89/83/9c/quan-vit-cu-chi.jpg",
      "latitude": 11.0061,
      "longitude": 106.63771,
      "has_delivery": false,
      "is_premium": false,
      "cuisines": [
        "Asian",
        "Vietnamese"
      ]
    },
    {
      "id": 12877264,
      "name": "Mini Indian restaurant",
      "link": "https://www.tripadvisor.com/Restaurant_Review-g3311194-d12877264-Reviews-Mini_Indian_restaurant-Thu_Dau_Mot_Binh_Duong_Province.html",
      "reviews": 11,
      "rating": 4.5,
      "price_range_usd": "$",
      "is_sponsored": false,
      "menu_link": null,
      "reservation_link": null,
      "featured_image": "https://dynamic-media-cdn.tripadvisor.com/media/photo-o/10/d2/87/ac/welcome.jpg",
      "latitude": 10.964705,
      "longitude": 106.66928,
      "has_delivery": false,
      "is_premium": false,
      "cuisines": [
        "Indian"
      ]
    },
    {
      "id": 33055994,
      "name": "Aroma Cocktail Bar",
      "link": "https://www.tripadvisor.com/Restaurant_Review-g3311194-d33055994-Reviews-Aroma_Cocktail_Bar-Thu_Dau_Mot_Binh_Duong_Province.html",
      "reviews": 5,
      "rating": 4.8,
      "price_range_usd": "$",
      "is_sponsored": false,
      "menu_link": null,
      "reservation_link": null,
      "featured_image": "https://dynamic-media-cdn.tripadvisor.com/media/photo-o/2f/93/2e/3b/caption.jpg",
      "latitude": 10.974292,
      "longitude": 106.66589,
      "has_delivery": false,
      "is_premium": false,
      "cuisines": [
        "Bar",
        "Pub"
      ]
    },
    {
      "id": 29011375,
      "name": "Hải Sản Ngọc Mai 5",
      "link": "https://www.tripadvisor.com/Restaurant_Review-g3311194-d29011375-Reviews-H_i_S_n_Ng_c_Mai_5-Thu_Dau_Mot_Binh_Duong_Province.html",
      "reviews": 1,
      "rating": 4,
      "price_range_usd": null,
      "is_sponsored": false,
      "menu_link": null,
      "reservation_link": null,
      "featured_image": "https://dynamic-media-cdn.tripadvisor.com/media/photo-o/2d/fa/26/e4/caption.jpg",
      "latitude": 11.028155,
      "longitude": 106.68018,
      "has_delivery": false,
      "is_premium": false,
      "cuisines": [
        "Seafood",
        "Vietnamese"
      ]
    },
    {
      "id": 28649742,
      "name": "Chú Ơi ! Grill",
      "link": "https://www.tripadvisor.com/Restaurant_Review-g3311194-d28649742-Reviews-Chu_Oi_Grill-Thu_Dau_Mot_Binh_Duong_Province.html",
      "reviews": 1,
      "rating": 5,
      "price_range_usd": "$$ - $$$",
      "is_sponsored": false,
      "menu_link": null,
      "reservation_link": null,
      "featured_image": "https://dynamic-media-cdn.tripadvisor.com/media/photo-o/2f/98/ef/73/chu-oi-grill.jpg",
      "latitude": 10.976435,
      "longitude": 106.67169,
      "has_delivery": false,
      "is_premium": false,
      "cuisines": [
        "Chinese",
        "Asian",
        "Korean"
      ]
    },
    {
      "id": 26550946,
      "name": "Akataiyo Sushi",
      "link": "https://www.tripadvisor.com/Restaurant_Review-g6748948-d26550946-Reviews-Akataiyo_Sushi-Di_An_Binh_Duong_Province.html",
      "reviews": 3,
      "rating": 5,
      "price_range_usd": null,
      "is_sponsored": false,
      "menu_link": null,
      "reservation_link": null,
      "featured_image": "https://dynamic-media-cdn.tripadvisor.com/media/photo-o/2a/1d/d1/d8/nha-hang-akataiyo-sushi.jpg",
      "latitude": 10.906395,
      "longitude": 106.7422,
      "has_delivery": false,
      "is_premium": false,
      "cuisines": [
        "Chinese",
        "Japanese",
        "Sushi",
        "Asian",
        "Korean"
      ]
    },
    {
      "id": 33008285,
      "name": "Nhà Hàng Tân Danh Nguyên",
      "link": "https://www.tripadvisor.com/Restaurant_Review-g3311194-d33008285-Reviews-Nha_Hang_Tan_Danh_Nguyen-Thu_Dau_Mot_Binh_Duong_Province.html",
      "reviews": 1,
      "rating": 4,
      "price_range_usd": null,
      "is_sponsored": false,
      "menu_link": null,
      "reservation_link": null,
      "featured_image": "https://dynamic-media-cdn.tripadvisor.com/media/photo-o/2f/54/0c/e5/caption.jpg",
      "latitude": 10.843955,
      "longitude": 106.77597,
      "has_delivery": false,
      "is_premium": false,
      "cuisines": [
        "Chinese"
      ]
    },
    {
      "id": 21381047,
      "name": "Akataiyo",
      "link": "https://www.tripadvisor.com/Restaurant_Review-g12693281-d21381047-Reviews-Akataiyo-Ben_Cat_Binh_Duong_Province.html",
      "reviews": 6,
      "rating": 5,
      "price_range_usd": "$$ - $$$",
      "is_sponsored": false,
      "menu_link": null,
      "reservation_link": null,
      "featured_image": "https://dynamic-media-cdn.tripadvisor.com/media/photo-o/1c/c0/40/04/akataiyo.jpg",
      "latitude": null,
      "longitude": null,
      "has_delivery": false,
      "is_premium": false,
      "cuisines": [
        "Japanese",
        "Japanese Fusion"
      ]
    },
    {
      "id": 26678285,
      "name": "BÚN CHẢ TÂY HỒ",
      "link": "https://www.tripadvisor.com/Restaurant_Review-g6748948-d26678285-Reviews-BUN_CH_TAY_H-Di_An_Binh_Duong_Province.html",
      "reviews": 4,
      "rating": 5,
      "price_range_usd": "$",
      "is_sponsored": false,
      "menu_link": null,
      "reservation_link": null,
      "featured_image": "https://dynamic-media-cdn.tripadvisor.com/media/photo-o/2a/6b/3d/55/mon-an-t-i-bun-ch-tay.jpg",
      "latitude": 10.89284,
      "longitude": 106.77142,
      "has_delivery": false,
      "is_premium": false,
      "cuisines": [
        "Cafe",
        "Asian",
        "Deli",
        "Indigenous"
      ]
    },
    {
      "id": 25094257,
      "name": "APES Craft Beer Restaurant Binh Duong",
      "link": "https://www.tripadvisor.com/Restaurant_Review-g3311194-d25094257-Reviews-APES_Craft_Beer_Restaurant_Binh_Duong-Thu_Dau_Mot_Binh_Duong_Province.html",
      "reviews": 1,
      "rating": 5,
      "price_range_usd": "$$$$",
      "is_sponsored": false,
      "menu_link": null,
      "reservation_link": null,
      "featured_image": "https://dynamic-media-cdn.tripadvisor.com/media/photo-o/27/e6/1e/d2/ribeye-steak.jpg",
      "latitude": 10.974974,
      "longitude": 106.66449,
      "has_delivery": false,
      "is_premium": false,
      "cuisines": [
        "Mexican",
        "Seafood",
        "British",
        "Deli"
      ]
    },
    {
      "id": 29272291,
      "name": "Mikado Sushi Aeon Mall Bình Dương",
      "link": "https://www.tripadvisor.com/Restaurant_Review-g11981259-d29272291-Reviews-Mikado_Sushi_Aeon_Mall_Binh_Duong-Thuan_An_Binh_Duong_Province.html",
      "reviews": 1,
      "rating": 5,
      "price_range_usd": null,
      "is_sponsored": false,
      "menu_link": null,
      "reservation_link": null,
      "featured_image": "https://dynamic-media-cdn.tripadvisor.com/media/photo-o/2e/27/19/60/caption.jpg",
      "latitude": 10.770483,
      "longitude": 106.66932,
      "has_delivery": false,
      "is_premium": false,
      "cuisines": [
        "Japanese",
        "Sushi",
        "Asian",
        "Korean",
        "Deli"
      ]
    },
    {
      "id": 24024915,
      "name": "saysua - drink & chill",
      "link": "https://www.tripadvisor.com/Restaurant_Review-g3311194-d24024915-Reviews-Saysua_drink_chill-Thu_Dau_Mot_Binh_Duong_Province.html",
      "reviews": 2,
      "rating": 5,
      "price_range_usd": null,
      "is_sponsored": false,
      "menu_link": null,
      "reservation_link": null,
      "featured_image": "https://dynamic-media-cdn.tripadvisor.com/media/photo-o/23/69/5d/52/the-counter.jpg",
      "latitude": 10.977128,
      "longitude": 106.674286,
      "has_delivery": false,
      "is_premium": false,
      "cuisines": [
        "Bar",
        "Pub",
        "Wine Bar"
      ]
    },
    {
      "id": 33088415,
      "name": "Nhà Hàng Happy 3",
      "link": "https://www.tripadvisor.com/Restaurant_Review-g3311194-d33088415-Reviews-Nha_Hang_Happy_3-Thu_Dau_Mot_Binh_Duong_Province.html",
      "reviews": 1,
      "rating": 4,
      "price_range_usd": null,
      "is_sponsored": false,
      "menu_link": null,
      "reservation_link": null,
      "featured_image": "https://dynamic-media-cdn.tripadvisor.com/media/photo-o/2f/af/00/69/caption.jpg",
      "latitude": 10.0095,
      "longitude": 105.750534,
      "has_delivery": false,
      "is_premium": false,
      "cuisines": [
        "Chinese",
        "Vietnamese"
      ]
    },
    {
      "id": 33059058,
      "name": "Buffet Poseidon Bình Dương",
      "link": "https://www.tripadvisor.com/Restaurant_Review-g3311194-d33059058-Reviews-Buffet_Poseidon_Binh_Duong-Thu_Dau_Mot_Binh_Duong_Province.html",
      "reviews": 0,
      "rating": 0,
      "price_range_usd": "$$ - $$$",
      "is_sponsored": false,
      "menu_link": "https://buffetposeidon.com/menu-buffet",
      "reservation_link": null,
      "featured_image": "https://dynamic-media-cdn.tripadvisor.com/media/photo-o/2f/8d/b4/19/nh-ng-mon-h-i-s-n-gia.jpg",
      "latitude": 20.938847,
      "longitude": 106.33406,
      "has_delivery": false,
      "is_premium": false,
      "cuisines": [
        "Japanese",
        "International",
        "Barbecue",
        "European",
        "Asian",
        "Vietnamese",
        "Indigenous"
      ]
    }
  ]
}