{
  "link": "https://www.tripadvisor.com/Restaurants-g1519989-Cao_Bang_Cao_Bang_Province.html",
  "total_pages": 2,
  "current_page": 1,
  "total_items_count": 33,
  "items_count": 30,
  "results": [
    {
      "id": 27143403,
      "name": "Bánh Mỳ Thu Thắng ",
      "link": "https://www.tripadvisor.com/Restaurant_Review-g1519989-d27143403-Reviews-Banh_M_Thu_Th_ng-Cao_Bang_Cao_Bang_Province.html",
      "reviews": 36,
      "rating": 5,
      "price_range_usd": "$$ - $$$",
      "is_sponsored": false,
      "menu_link": null,
      "reservation_link": null,
      "featured_image": "https://dynamic-media-cdn.tripadvisor.com/media/photo-o/2e/87/29/8e/caption.jpg",
      "latitude": 22.664099,
      "longitude": 106.260506,
      "has_delivery": false,
      "is_premium": false,
      "cuisines": [
        "Asian",
        "Deli",
        "Vietnamese",
        "Healthy",
        "Indigenous"
      ]
    },
    {
      "id": 33093002,
      "name": "Cao Bằng Eco Bistro & Stay",
      "link": "https://www.tripadvisor.com/Restaurant_Review-g1519989-d33093002-Reviews-Cao_B_ng_Eco_Bistro_Stay-Cao_Bang_Cao_Bang_Province.html",
      "reviews": 16,
      "rating": 5,
      "price_range_usd": null,
      "is_sponsored": false,
      "menu_link": null,
      "reservation_link": null,
      "featured_image": "https://dynamic-media-cdn.tripadvisor.com/media/photo-o/2f/e8/4e/d5/caption.jpg",
      "latitude": 22.66328,
      "longitude": 106.26075,
      "has_delivery": false,
      "is_premium": false,
      "cuisines": [
        "Pizza"
      ]
    },
    {
      "id": 12338176,
      "name": "Pedro's Pizza",
      "link": "https://www.tripadvisor.com/Restaurant_Review-g1519989-d12338176-Reviews-Pedro_s_Pizza-Cao_Bang_Cao_Bang_Province.html",
      "reviews": 113,
      "rating": 4.8,
      "price_range_usd": "$$ - $$$",
      "is_sponsored": false,
      "menu_link": null,
      "reservation_link": null,
      "featured_image": "https://dynamic-media-cdn.tripadvisor.com/media/photo-o/12/0b/22/a4/new-look-for-2018.jpg",
      "latitude": 22.667301,
      "longitude": 106.26154,
      "has_delivery": false,
      "is_premium": false,
      "cuisines": [
        "Pizza"
      ]
    },
    {
      "id": 5547643,
      "name": "Pizza & Beefsteak Chi",
      "link": "https://www.tripadvisor.com/Restaurant_Review-g1519989-d5547643-Reviews-Pizza_Beefsteak_Chi-Cao_Bang_Cao_Bang_Province.html",
      "reviews": 69,
      "rating": 4.4,
      "price_range_usd": "$",
      "is_sponsored": false,
      "menu_link": null,
      "reservation_link": null,
      "featured_image": "https://dynamic-media-cdn.tripadvisor.com/media/photo-o/23/5b/b2/ef/new-location.jpg",
      "latitude": 22.670076,
      "longitude": 106.25922,
      "has_delivery": false,
      "is_premium": false,
      "cuisines": [
        "Italian",
        "Pizza"
      ]
    },
    {
      "id": 25416379,
      "name": "Yên - ngon như mẹ nấu",
      "link": "https://www.tripadvisor.com/Restaurant_Review-g1519989-d25416379-Reviews-Yen_ngon_nhu_m_n_u-Cao_Bang_Cao_Bang_Province.html",
      "reviews": 4,
      "rating": 5,
      "price_range_usd": null,
      "is_sponsored": false,
      "menu_link": null,
      "reservation_link": null,
      "featured_image": "https://dynamic-media-cdn.tripadvisor.com/media/photo-o/29/59/f0/84/yen.jpg",
      "latitude": 22.66499,
      "longitude": 106.26085,
      "has_delivery": false,
      "is_premium": false,
      "cuisines": [
        "Pub",
        "Fusion",
        "Vietnamese",
        "Gastropub",
        "Street Food",
        "Indigenous"
      ]
    },
    {
      "id": 12703235,
      "name": "Toc ca phe",
      "link": "https://www.tripadvisor.com/Restaurant_Review-g1519989-d12703235-Reviews-Toc_ca_phe-Cao_Bang_Cao_Bang_Province.html",
      "reviews": 15,
      "rating": 4.3,
      "price_range_usd": "$",
      "is_sponsored": false,
      "menu_link": null,
      "reservation_link": null,
      "featured_image": "https://dynamic-media-cdn.tripadvisor.com/media/photo-o/11/7f/73/a9/toc-ca-phe.jpg",
      "latitude": 22.660517,
      "longitude": 106.25972,
      "has_delivery": false,
      "is_premium": false,
      "cuisines": [
        "Cafe"
      ]
    },
    {
      "id": 33024148,
      "name": "Quán Ngói Cao Bằng",
      "link": "https://www.tripadvisor.com/Restaurant_Review-g1519989-d33024148-Reviews-Quan_Ngoi_Cao_B_ng-Cao_Bang_Cao_Bang_Province.html",
      "reviews": 1,
      "rating": 5,
      "price_range_usd": null,
      "is_sponsored": false,
      "menu_link": null,
      "reservation_link": null,
      "featured_image": "https://dynamic-media-cdn.tripadvisor.com/media/photo-o/2f/84/c2/99/th-t-tuy-t-v-i-v-i-khong.jpg",
      "latitude": 22.66328,
      "longitude": 106.26075,
      "has_delivery": false,
      "is_premium": false,
      "cuisines": []
    },
    {
      "id": 25175797,
      "name": "The 8th Rooftop Bar Cafe",
      "link": "https://www.tripadvisor.com/Restaurant_Review-g1519989-d25175797-Reviews-The_8th_Rooftop_Bar_Cafe-Cao_Bang_Cao_Bang_Province.html",
      "reviews": 2,
      "rating": 5,
      "price_range_usd": null,
      "is_sponsored": false,
      "menu_link": null,
      "reservation_link": null,
      "featured_image": "https://dynamic-media-cdn.tripadvisor.com/media/photo-o/27/2b/b1/88/night-view.jpg",
      "latitude": 22.665901,
      "longitude": 106.25638,
      "has_delivery": false,
      "is_premium": false,
      "cuisines": [
        "Italian",
        "Vietnamese"
      ]
    },
    {
      "id": 10794548,
      "name": "Moc Quan Restaurant",
      "link": "https://www.tripadvisor.com/Restaurant_Review-g1519989-d10794548-Reviews-Moc_Quan_Restaurant-Cao_Bang_Cao_Bang_Province.html",
      "reviews": 6,
      "rating": 4.7,
      "price_range_usd": null,
      "is_sponsored": false,
      "menu_link": null,
      "reservation_link": null,
      "featured_image": "https://dynamic-media-cdn.tripadvisor.com/media/photo-o/0d/27/11/48/nha-hang-m-c-quan.jpg",
      "latitude": 22.66871,
      "longitude": 106.25484,
      "has_delivery": false,
      "is_premium": false,
      "cuisines": []
    },
    {
      "id": 13818102,
      "name": "La Stella",
      "link": "https://www.tripadvisor.com/Restaurant_Review-g1519989-d13818102-Reviews-La_Stella-Cao_Bang_Cao_Bang_Province.html",
      "reviews": 2,
      "rating": 5,
      "price_range_usd": "$",
      "is_sponsored": false,
      "menu_link": null,
      "reservation_link": null,
      "featured_image": "https://dynamic-media-cdn.tripadvisor.com/media/photo-o/12/50/3d/8f/getlstd-property-photo.jpg",
      "latitude": 22.658962,
      "longitude": 106.26601,
      "has_delivery": false,
      "is_premium": false,
      "cuisines": [
        "Brew Pub",
        "Cafe",
        "Fast Food",
        "Asian",
        "Korean",
        "Pub"
      ]
    },
    {
      "id": 8126612,
      "name": "A Dong BBQ Pizza",
      "link": "https://www.tripadvisor.com/Restaurant_Review-g1519989-d8126612-Reviews-A_Dong_BBQ_Pizza-Cao_Bang_Cao_Bang_Province.html",
      "reviews": 5,
      "rating": 4,
      "price_range_usd": "$",
      "is_sponsored": false,
      "menu_link": null,
      "reservation_link": null,
      "featured_image": "https://dynamic-media-cdn.tripadvisor.com/media/photo-o/17/45/c3/2e/customer.jpg",
      "latitude": 22.665085,
      "longitude": 106.25643,
      "has_delivery": false,
      "is_premium": false,
      "cuisines": [
        "Pizza",
        "Fast Food",
        "Deli",
        "Singaporean"
      ]
    },
    {
      "id": 12292840,
      "name": "Anh Tuan Restaurant",
      "link": "https://www.tripadvisor.com/Restaurant_Review-g1519989-d12292840-Reviews-Anh_Tuan_Restaurant-Cao_Bang_Cao_Bang_Province.html",
      "reviews": 4,
      "rating": 4.5,
      "price_range_usd": "$",
      "is_sponsored": false,
      "menu_link": null,
      "reservation_link": null,
      "featured_image": "https://dynamic-media-cdn.tripadvisor.com/media/photo-o/15/24/6b/dd/spring-rolls-and-pork.jpg",
      "latitude": null,
      "longitude": null,
      "has_delivery": false,
      "is_premium": false,
      "cuisines": [
        "Vietnamese"
      ]
    },
    {
      "id": 14976055,
      "name": "Com Phuot Cao Bang",
      "link": "https://www.tripadvisor.com/Restaurant_Review-g1519989-d14976055-Reviews-Com_Phuot_Cao_Bang-Cao_Bang_Cao_Bang_Province.html",
      "reviews": 1,
      "rating": 5,
      "price_range_usd": "$",
      "is_sponsored": false,
      "menu_link": null,
      "reservation_link": null,
      "featured_image": "https://dynamic-media-cdn.tripadvisor.com/media/photo-o/1c/29/df/69/com-phu-t-kinh-chao-quy.jpg",
      "latitude": 22.66725,
      "longitude": 106.26072,
      "has_delivery": false,
      "is_premium": false,
      "cuisines": [
        "Vietnamese"
      ]
    },
    {
      "id": 17707135,
      "name": "Com Thu Ngan",
      "link": "https://www.tripadvisor.com/Restaurant_Review-g1519989-d17707135-Reviews-Com_Thu_Ngan-Cao_Bang_Cao_Bang_Province.html",
      "reviews": 2,
      "rating": 5,
      "price_range_usd": null,
      "is_sponsored": false,
      "menu_link": null,
      "reservation_link": null,
      "featured_image": "https://dynamic-media-cdn.tripadvisor.com/media/photo-o/18/36/35/45/mixed-asian-style-buffet.jpg",
      "latitude": 22.66683,
      "longitude": 106.26083,
      "has_delivery": false,
      "is_premium": false,
      "cuisines": [
        "Chinese",
        "Vietnamese"
      ]
    },
    {
      "id": 15357246,
      "name": "Nha Hang - Hotel - Karaoke - Cafe 34 Nga Luong",
      "link": "https://www.tripadvisor.com/Restaurant_Review-g1519989-d15357246-Reviews-Nha_Hang_Hotel_Karaoke_Cafe_34_Nga_Luong-Cao_Bang_Cao_Bang_Province.html",
      "reviews": 2,
      "rating": 5,
      "price_range_usd": null,
      "is_sponsored": false,
      "menu_link": null,
      "reservation_link": null,
      "featured_image": "https://dynamic-media-cdn.tripadvisor.com/media/photo-o/17/ea/c9/b3/photo0jpg.jpg",
      "latitude": 22.673288,
      "longitude": 106.24646,
      "has_delivery": false,
      "is_premium": false,
      "cuisines": [
        "Fusion"
      ]
    },
    {
      "id": 26778256,
      "name": "Vegetarian - Vegan - Chay",
      "link": "https://www.tripadvisor.com/Restaurant_Review-g1519989-d26778256-Reviews-Vegetarian_Vegan_Chay-Cao_Bang_Cao_Bang_Province.html",
      "reviews": 1,
      "rating": 5,
      "price_range_usd": null,
      "is_sponsored": false,
      "menu_link": null,
      "reservation_link": null,
      "featured_image": "https://dynamic-media-cdn.tripadvisor.com/media/photo-o/2b/4c/2c/24/caption.jpg",
      "latitude": 22.656137,
      "longitude": 106.26314,
      "has_delivery": false,
      "is_premium": false,
      "cuisines": [
        "Vietnamese"
      ]
    },
    {
      "id": 17838803,
      "name": "Lương Sơn Quán",
      "link": "https://www.tripadvisor.com/Restaurant_Review-g1519989-d17838803-Reviews-Luong_Son_Quan-Cao_Bang_Cao_Bang_Province.html",
      "reviews": 1,
      "rating": 5,
      "price_range_usd": null,
      "is_sponsored": false,
      "menu_link": null,
      "reservation_link": null,
      "featured_image": "https://dynamic-media-cdn.tripadvisor.com/media/photo-o/21/83/49/a3/nh-ng-bong-hoa-r-c-r.jpg",
      "latitude": 22.67556,
      "longitude": 106.25128,
      "has_delivery": false,
      "is_premium": false,
      "cuisines": [
        "Asian"
      ]
    },
    {
      "id": 6898663,
      "name": "huong sen, cao bang, vietnam",
      "link": "https://www.tripadvisor.com/Restaurant_Review-g1519989-d6898663-Reviews-Huong_sen_cao_bang_vietnam-Cao_Bang_Cao_Bang_Province.html",
      "reviews": 5,
      "rating": 3.6,
      "price_range_usd": "$",
      "is_sponsored": false,
      "menu_link": null,
      "reservation_link": null,
      "featured_image": "https://dynamic-media-cdn.tripadvisor.com/media/photo-o/06/3b/a4/ba/getlstd-property-photo_rotated_90.jpg",
      "latitude": 22.66306,
      "longitude": 106.26015,
      "has_delivery": false,
      "is_premium": false,
      "cuisines": [
        "Vietnamese"
      ]
    },
    {
      "id": 11955357,
      "name": "Nga Ba Song - Lau Thuc Yen",
      "link": "https://www.tripadvisor.com/Restaurant_Review-g1519989-d11955357-Reviews-Nga_Ba_Song_Lau_Thuc_Yen-Cao_Bang_Cao_Bang_Province.html",
      "reviews": 1,
      "rating": 4,
      "price_range_usd": "$",
      "is_sponsored": false,
      "menu_link": null,
      "reservation_link": null,
      "featured_image": "https://dynamic-media-cdn.tripadvisor.com/media/photo-o/0e/56/a9/e1/t-ng-2.jpg",
      "latitude": 22.673626,
      "longitude": 106.25387,
      "has_delivery": false,
      "is_premium": false,
      "cuisines": [
        "Seafood",
        "Deli",
        "Pub",
        "Vietnamese",
        "Diner",
        "Gastropub"
      ]
    },
    {
      "id": 15009371,
      "name": "Thu Tuong Restaurant",
      "link": "https://www.tripadvisor.com/Restaurant_Review-g1519989-d15009371-Reviews-Thu_Tuong_Restaurant-Cao_Bang_Cao_Bang_Province.html",
      "reviews": 1,
      "rating": 4,
      "price_range_usd": null,
      "is_sponsored": false,
      "menu_link": null,
      "reservation_link": null,
      "featured_image": null,
      "latitude": 22.668474,
      "longitude": 106.25656,
      "has_delivery": false,
      "is_premium": false,
      "cuisines": [
        "Vietnamese"
      ]
    },
    {
      "id": 19244127,
      "name": "Pho Nuong HT - BBQ & Beer",
      "link": "https://www.tripadvisor.com/Restaurant_Review-g1519989-d19244127-Reviews-Pho_Nuong_HT_BBQ_Beer-Cao_Bang_Cao_Bang_Province.html",
      "reviews": 3,
      "rating": 3.7,
      "price_range_usd": null,
      "is_sponsored": false,
      "menu_link": null,
      "reservation_link": null,
      "featured_image": "https://dynamic-media-cdn.tripadvisor.com/media/photo-o/1a/34/72/65/front-entrance-don-t.jpg",
      "latitude": 22.66306,
      "longitude": 106.26015,
      "has_delivery": false,
      "is_premium": false,
      "cuisines": [
        "American",
        "Asian",
        "Vietnamese"
      ]
    },
    {
      "id": 17750068,
      "name": "Gia Cung Quan",
      "link": "https://www.tripadvisor.com/Restaurant_Review-g1519989-d17750068-Reviews-Gia_Cung_Quan-Cao_Bang_Cao_Bang_Province.html",
      "reviews": 0,
      "rating": 0,
      "price_range_usd": null,
      "is_sponsored": false,
      "menu_link": "https://sites.google.com/view/giacungquan",
      "reservation_link": null,
      "featured_image": "https://dynamic-media-cdn.tripadvisor.com/media/photo-o/18/5d/57/bc/l-i-vao-chinh.jpg",
      "latitude": 22.673231,
      "longitude": 106.24853,
      "has_delivery": false,
      "is_premium": false,
      "cuisines": [
        "Brew Pub",
        "Deli",
        "Pub",
        "Vietnamese",
        "Healthy",
        "Gastropub"
      ]
    },
    {
      "id": 25008946,
      "name": "Hat Dé Quàn",
      "link": "https://www.tripadvisor.com/Restaurant_Review-g1519989-d25008946-Reviews-Hat_De_Quan-Cao_Bang_Cao_Bang_Province.html",
      "reviews": 2,
      "rating": 2.5,
      "price_range_usd": null,
      "is_sponsored": false,
      "menu_link": null,
      "reservation_link": null,
      "featured_image": null,
      "latitude": 22.666737,
      "longitude": 106.260826,
      "has_delivery": false,
      "is_premium": false,
      "cuisines": [
        "Vietnamese"
      ]
    },
    {
      "id": 26572512,
      "name": "The Old Fashioned",
      "link": "https://www.tripadvisor.com/Restaurant_Review-g1519989-d26572512-Reviews-The_Old_Fashioned-Cao_Bang_Cao_Bang_Province.html",
      "reviews": 0,
      "rating": 0,
      "price_range_usd": null,
      "is_sponsored": false,
      "menu_link": null,
      "reservation_link": null,
      "featured_image": null,
      "latitude": 22.667358,
      "longitude": 106.25729,
      "has_delivery": false,
      "is_premium": false,
      "cuisines": [
        "Bar",
        "Pub",
        "Wine Bar"
      ]
    },
    {
      "id": 13975412,
      "name": "Tam Food",
      "link": "https://www.tripadvisor.com/Restaurant_Review-g1519989-d13975412-Reviews-Tam_Food-Cao_Bang_Cao_Bang_Province.html",
      "reviews": 1,
      "rating": 3,
      "price_range_usd": null,
      "is_sponsored": false,
      "menu_link": null,
      "reservation_link": null,
      "featured_image": null,
      "latitude": 22.665894,
      "longitude": 106.2543,
      "has_delivery": false,
      "is_premium": false,
      "cuisines": [
        "American",
        "Vietnamese"
      ]
    },
    {
      "id": 17694971,
      "name": "Am Thuc Cung Dình",
      "link": "https://www.tripadvisor.com/Restaurant_Review-g1519989-d17694971-Reviews-Am_Thuc_Cung_Dinh-Cao_Bang_Cao_Bang_Province.html",
      "reviews": 0,
      "rating": 0,
      "price_range_usd": "$$ - $$$",
      "is_sponsored": false,
      "menu_link": null,
      "reservation_link": null,
      "featured_image": "https://dynamic-media-cdn.tripadvisor.com/media/photo-o/18/18/72/cd/getlstd-property-photo.jpg",
      "latitude": 22.673016,
      "longitude": 106.24861,
      "has_delivery": false,
      "is_premium": false,
      "cuisines": []
    },
    {
      "id": 12328981,
      "name": "Huong Thinh",
      "link": "https://www.tripadvisor.com/Restaurant_Review-g1519989-d12328981-Reviews-Huong_Thinh-Cao_Bang_Cao_Bang_Province.html",
      "reviews": 1,
      "rating": 3,
      "price_range_usd": null,
      "is_sponsored": false,
      "menu_link": null,
      "reservation_link": null,
      "featured_image": null,
      "latitude": 22.66718,
      "longitude": 106.25828,
      "has_delivery": false,
      "is_premium": false,
      "cuisines": []
    },
    {
      "id": 15579493,
      "name": "Banh Thanh Do So 1",
      "link": "https://www.tripadvisor.com/Restaurant_Review-g1519989-d15579493-Reviews-Banh_Thanh_Do_So_1-Cao_Bang_Cao_Bang_Province.html",
      "reviews": 0,
      "rating": 0,
      "price_range_usd": "$",
      "is_sponsored": false,
      "menu_link": null,
      "reservation_link": null,
      "featured_image": null,
      "latitude": 22.665478,
      "longitude": 106.26119,
      "has_delivery": false,
      "is_premium": false,
      "cuisines": [
        "Pizza"
      ]
    },
    {
      "id": 14100621,
      "name": "Hien Tu Quan",
      "link": "https://www.tripadvisor.com/Restaurant_Review-g1519989-d14100621-Reviews-Hien_Tu_Quan-Cao_Bang_Cao_Bang_Province.html",
      "reviews": 0,
      "rating": 0,
      "price_range_usd": null,
      "is_sponsored": false,
      "menu_link": null,
      "reservation_link": null,
      "featured_image": null,
      "latitude": 22.676563,
      "longitude": 106.24166,
      "has_delivery": false,
      "is_premium": false,
      "cuisines": [
        "Vietnamese"
      ]
    },
    {
      "id": 17427106,
      "name": "Nhà Hàng Ẩm Thực",
      "link": "https://www.tripadvisor.com/Restaurant_Review-g1519989-d17427106-Reviews-Nha_Hang_m_Th_c-Cao_Bang_Cao_Bang_Province.html",
      "reviews": 0,
      "rating": 0,
      "price_range_usd": null,
      "is_sponsored": false,
      "menu_link": null,
      "reservation_link": null,
      "featured_image": "https://dynamic-media-cdn.tripadvisor.com/media/photo-o/17/fe/99/35/review.jpg",
      "latitude": 22.679985,
      "longitude": 106.22266,
      "has_delivery": false,
      "is_premium": false,
      "cuisines": [
        "Vietnamese",
        "Healthy"
      ]
    }
  ]
}