{
  "link": "https://www.tripadvisor.com/Restaurants-g2146235-Nghe_An_Province.html",
  "total_pages": 3,
  "current_page": 1,
  "total_items_count": 65,
  "items_count": 30,
  "results": [
    {
      "id": 18970342,
      "name": "Lan Chau Restaurant",
      "link": "https://www.tripadvisor.com/Restaurant_Review-g4235728-d18970342-Reviews-Lan_Chau_Restaurant-Cua_Lo_Nghe_An_Province.html",
      "reviews": 11,
      "rating": 4.7,
      "price_range_usd": "$$ - $$$",
      "is_sponsored": false,
      "menu_link": "https://songnguson.vn/xuan-thanh.html",
      "reservation_link": null,
      "featured_image": "https://dynamic-media-cdn.tripadvisor.com/media/photo-o/19/ce/f8/67/ban-cong-t-ng-2-nha-hang.jpg",
      "latitude": 18.820253,
      "longitude": 105.72159,
      "has_delivery": false,
      "is_premium": false,
      "cuisines": [
        "Seafood",
        "European",
        "Asian",
        "Vietnamese",
        "Healthy"
      ]
    },
    {
      "id": 16871317,
      "name": "Nha Hang Van Chai - Seafood Restaurant",
      "link": "https://www.tripadvisor.com/Restaurant_Review-g1554764-d16871317-Reviews-Nha_Hang_Van_Chai_Seafood_Restaurant-Vinh_Nghe_An_Province.html",
      "reviews": 5,
      "rating": 4.6,
      "price_range_usd": "$",
      "is_sponsored": false,
      "menu_link": null,
      "reservation_link": null,
      "featured_image": "https://dynamic-media-cdn.tripadvisor.com/media/photo-o/16/eb/f5/97/m-t-tru-c-c-a-nha-hang.jpg",
      "latitude": 18.697105,
      "longitude": 105.68583,
      "has_delivery": false,
      "is_premium": false,
      "cuisines": [
        "Brew Pub",
        "Bar",
        "Seafood",
        "Asian",
        "Deli",
        "Pub",
        "Vietnamese",
        "Wine Bar"
      ]
    },
    {
      "id": 13975482,
      "name": "Luon Cay Gia Truyen Phuong Dao",
      "link": "https://www.tripadvisor.com/Restaurant_Review-g4235728-d13975482-Reviews-Luon_Cay_Gia_Truyen_Phuong_Dao-Cua_Lo_Nghe_An_Province.html",
      "reviews": 12,
      "rating": 4.8,
      "price_range_usd": "$",
      "is_sponsored": false,
      "menu_link": null,
      "reservation_link": null,
      "featured_image": "https://dynamic-media-cdn.tripadvisor.com/media/photo-o/12/95/ff/53/getlstd-property-photo.jpg",
      "latitude": 18.804487,
      "longitude": 105.72132,
      "has_delivery": false,
      "is_premium": false,
      "cuisines": [
        "Fast Food",
        "European",
        "Asian",
        "Korean",
        "Vietnamese"
      ]
    },
    {
      "id": 17157808,
      "name": "The American Steak Restaurant",
      "link": "https://www.tripadvisor.com/Restaurant_Review-g1554764-d17157808-Reviews-The_American_Steak_Restaurant-Vinh_Nghe_An_Province.html",
      "reviews": 25,
      "rating": 4.4,
      "price_range_usd": "$$ - $$$",
      "is_sponsored": false,
      "menu_link": null,
      "reservation_link": null,
      "featured_image": "https://dynamic-media-cdn.tripadvisor.com/media/photo-o/17/13/c3/e5/20190407-203716-largejpg.jpg",
      "latitude": 18.666714,
      "longitude": 105.68167,
      "has_delivery": false,
      "is_premium": false,
      "cuisines": [
        "Steakhouse"
      ]
    },
    {
      "id": 26321561,
      "name": "Nhà hàng Nemo Sóng xanh",
      "link": "https://www.tripadvisor.com/Restaurant_Review-g1554764-d26321561-Reviews-Nha_hang_Nemo_Song_xanh-Vinh_Nghe_An_Province.html",
      "reviews": 2,
      "rating": 5,
      "price_range_usd": null,
      "is_sponsored": false,
      "menu_link": null,
      "reservation_link": null,
      "featured_image": "https://dynamic-media-cdn.tripadvisor.com/media/photo-o/29/af/f9/b6/anh-ngoai-nha-hang.jpg",
      "latitude": 18.658634,
      "longitude": 105.67821,
      "has_delivery": false,
      "is_premium": false,
      "cuisines": [
        "Seafood",
        "Barbecue",
        "European",
        "Thai",
        "Indigenous"
      ]
    },
    {
      "id": 14199127,
      "name": "Nha Hang Ga Thanh Chuong",
      "link": "https://www.tripadvisor.com/Restaurant_Review-g1554764-d14199127-Reviews-Nha_Hang_Ga_Thanh_Chuong-Vinh_Nghe_An_Province.html",
      "reviews": 5,
      "rating": 4,
      "price_range_usd": "$",
      "is_sponsored": false,
      "menu_link": null,
      "reservation_link": null,
      "featured_image": "https://dynamic-media-cdn.tripadvisor.com/media/photo-o/15/30/51/33/ga-khong-l-i-thoat.jpg",
      "latitude": 18.65909,
      "longitude": 105.67758,
      "has_delivery": false,
      "is_premium": false,
      "cuisines": [
        "Fast Food",
        "Deli"
      ]
    },
    {
      "id": 14199266,
      "name": "Nha Hang Ga Thanh Chuong 2",
      "link": "https://www.tripadvisor.com/Restaurant_Review-g1554764-d14199266-Reviews-Nha_Hang_Ga_Thanh_Chuong_2-Vinh_Nghe_An_Province.html",
      "reviews": 5,
      "rating": 4.2,
      "price_range_usd": "$",
      "is_sponsored": false,
      "menu_link": null,
      "reservation_link": null,
      "featured_image": "https://dynamic-media-cdn.tripadvisor.com/media/photo-o/15/28/ac/be/ga-khong-l-i-thoat.jpg",
      "latitude": 18.659086,
      "longitude": 105.67758,
      "has_delivery": false,
      "is_premium": false,
      "cuisines": [
        "Deli"
      ]
    },
    {
      "id": 17704139,
      "name": "Padma Restaurant",
      "link": "https://www.tripadvisor.com/Restaurant_Review-g4235728-d17704139-Reviews-Padma_Restaurant-Cua_Lo_Nghe_An_Province.html",
      "reviews": 4,
      "rating": 5,
      "price_range_usd": "$",
      "is_sponsored": false,
      "menu_link": null,
      "reservation_link": null,
      "featured_image": "https://dynamic-media-cdn.tripadvisor.com/media/photo-o/18/87/fc/45/nha-hang-padma.jpg",
      "latitude": 18.7712,
      "longitude": 105.756584,
      "has_delivery": false,
      "is_premium": false,
      "cuisines": [
        "Seafood",
        "European",
        "Asian",
        "Vietnamese"
      ]
    },
    {
      "id": 19042286,
      "name": "Nha Hang Huong Son 69 Cua Lo",
      "link": "https://www.tripadvisor.com/Restaurant_Review-g4235728-d19042286-Reviews-Nha_Hang_Huong_Son_69_Cua_Lo-Cua_Lo_Nghe_An_Province.html",
      "reviews": 1,
      "rating": 5,
      "price_range_usd": null,
      "is_sponsored": false,
      "menu_link": null,
      "reservation_link": null,
      "featured_image": "https://dynamic-media-cdn.tripadvisor.com/media/photo-o/19/61/5d/4d/wonderful-place-very.jpg",
      "latitude": null,
      "longitude": null,
      "has_delivery": false,
      "is_premium": false,
      "cuisines": [
        "Seafood",
        "Vietnamese",
        "Soups"
      ]
    },
    {
      "id": 7070091,
      "name": "Gogi House",
      "link": "https://www.tripadvisor.com/Restaurant_Review-g1554764-d7070091-Reviews-Gogi_House-Vinh_Nghe_An_Province.html",
      "reviews": 21,
      "rating": 4.2,
      "price_range_usd": "$$ - $$$",
      "is_sponsored": false,
      "menu_link": "http://gogi.com.vn/menus/thuc-don-gogi/",
      "reservation_link": null,
      "featured_image": "https://dynamic-media-cdn.tripadvisor.com/media/photo-o/11/16/46/17/photo0jpg.jpg",
      "latitude": 18.675072,
      "longitude": 105.67435,
      "has_delivery": false,
      "is_premium": false,
      "cuisines": [
        "Barbecue",
        "Asian",
        "Korean",
        "Grill"
      ]
    },
    {
      "id": 16813042,
      "name": "Nha Hang Hai San Bien Xanh",
      "link": "https://www.tripadvisor.com/Restaurant_Review-g1554764-d16813042-Reviews-Nha_Hang_Hai_San_Bien_Xanh-Vinh_Nghe_An_Province.html",
      "reviews": 4,
      "rating": 4.8,
      "price_range_usd": "$$ - $$$",
      "is_sponsored": false,
      "menu_link": null,
      "reservation_link": null,
      "featured_image": "https://dynamic-media-cdn.tripadvisor.com/media/photo-o/16/cd/de/ad/co-s-2.jpg",
      "latitude": 18.676424,
      "longitude": 105.673065,
      "has_delivery": false,
      "is_premium": false,
      "cuisines": [
        "Seafood"
      ]
    },
    {
      "id": 14041608,
      "name": "Nha hang Hai San Dai Duong",
      "link": "https://www.tripadvisor.com/Restaurant_Review-g1554764-d14041608-Reviews-Nha_hang_Hai_San_Dai_Duong-Vinh_Nghe_An_Province.html",
      "reviews": 3,
      "rating": 4.7,
      "price_range_usd": "$$ - $$$",
      "is_sponsored": false,
      "menu_link": null,
      "reservation_link": null,
      "featured_image": "https://dynamic-media-cdn.tripadvisor.com/media/photo-o/12/c1/71/d9/getlstd-property-photo.jpg",
      "latitude": 18.709217,
      "longitude": 105.678505,
      "has_delivery": false,
      "is_premium": false,
      "cuisines": [
        "Caribbean",
        "Seafood",
        "European",
        "Deli",
        "Vietnamese",
        "Bahamian",
        "Central European"
      ]
    },
    {
      "id": 12621390,
      "name": "Gin' Pizza",
      "link": "https://www.tripadvisor.com/Restaurant_Review-g1554764-d12621390-Reviews-Gin_Pizza-Vinh_Nghe_An_Province.html",
      "reviews": 12,
      "rating": 4.6,
      "price_range_usd": null,
      "is_sponsored": false,
      "menu_link": null,
      "reservation_link": null,
      "featured_image": "https://dynamic-media-cdn.tripadvisor.com/media/photo-o/0f/e4/c5/c8/photo0jpg.jpg",
      "latitude": 18.666174,
      "longitude": 105.70191,
      "has_delivery": false,
      "is_premium": false,
      "cuisines": [
        "Italian",
        "Pizza"
      ]
    },
    {
      "id": 12269249,
      "name": "Sura BBQ Restaurant",
      "link": "https://www.tripadvisor.com/Restaurant_Review-g1554764-d12269249-Reviews-Sura_BBQ_Restaurant-Vinh_Nghe_An_Province.html",
      "reviews": 8,
      "rating": 4.4,
      "price_range_usd": null,
      "is_sponsored": false,
      "menu_link": null,
      "reservation_link": null,
      "featured_image": "https://dynamic-media-cdn.tripadvisor.com/media/photo-o/0e/d5/a7/a7/d-nu-ng-th-ga-nha.jpg",
      "latitude": 18.66586,
      "longitude": 105.67909,
      "has_delivery": false,
      "is_premium": false,
      "cuisines": []
    },
    {
      "id": 19546742,
      "name": "Sen Que Restaurant",
      "link": "https://www.tripadvisor.com/Restaurant_Review-g19578504-d19546742-Reviews-Sen_Que_Restaurant-Kim_Lien_Nghe_An_Province.html",
      "reviews": 1,
      "rating": 5,
      "price_range_usd": "$$ - $$$",
      "is_sponsored": false,
      "menu_link": null,
      "reservation_link": null,
      "featured_image": "https://dynamic-media-cdn.tripadvisor.com/media/photo-o/1a/52/53/a5/m-t-phong-c-a-nha-hang.jpg",
      "latitude": 18.68529,
      "longitude": 105.569626,
      "has_delivery": false,
      "is_premium": false,
      "cuisines": [
        "Seafood",
        "Asian",
        "Pub",
        "Vietnamese",
        "Gastropub",
        "Beer restaurants"
      ]
    },
    {
      "id": 27136449,
      "name": "Aota Garden ",
      "link": "https://www.tripadvisor.com/Restaurant_Review-g1554764-d27136449-Reviews-Aota_Garden-Vinh_Nghe_An_Province.html",
      "reviews": 2,
      "rating": 5,
      "price_range_usd": null,
      "is_sponsored": false,
      "menu_link": null,
      "reservation_link": null,
      "featured_image": "https://dynamic-media-cdn.tripadvisor.com/media/photo-o/2b/41/71/2b/caption.jpg",
      "latitude": 18.677069,
      "longitude": 105.69164,
      "has_delivery": false,
      "is_premium": false,
      "cuisines": [
        "Vietnamese"
      ]
    },
    {
      "id": 4773910,
      "name": "Saigon Kim Lien Restaurant",
      "link": "https://www.tripadvisor.com/Restaurant_Review-g1554764-d4773910-Reviews-Saigon_Kim_Lien_Restaurant-Vinh_Nghe_An_Province.html",
      "reviews": 25,
      "rating": 3.8,
      "price_range_usd": "$$ - $$$",
      "is_sponsored": false,
      "menu_link": null,
      "reservation_link": null,
      "featured_image": "https://dynamic-media-cdn.tripadvisor.com/media/photo-o/09/fb/46/47/photo0jpg.jpg",
      "latitude": 18.67106,
      "longitude": 105.6741,
      "has_delivery": false,
      "is_premium": false,
      "cuisines": [
        "Asian",
        "Vietnamese"
      ]
    },
    {
      "id": 17379458,
      "name": "Nha Hang Son Que - Tu Nam 1999",
      "link": "https://www.tripadvisor.com/Restaurant_Review-g1554764-d17379458-Reviews-Nha_Hang_Son_Que_Tu_Nam_1999-Vinh_Nghe_An_Province.html",
      "reviews": 2,
      "rating": 5,
      "price_range_usd": null,
      "is_sponsored": false,
      "menu_link": null,
      "reservation_link": null,
      "featured_image": "https://dynamic-media-cdn.tripadvisor.com/media/photo-o/17/3e/c4/89/getlstd-property-photo.jpg",
      "latitude": 18.67757,
      "longitude": 105.59209,
      "has_delivery": false,
      "is_premium": false,
      "cuisines": []
    },
    {
      "id": 6028218,
      "name": "Miao's Pizza",
      "link": "https://www.tripadvisor.com/Restaurant_Review-g1554764-d6028218-Reviews-Miao_s_Pizza-Vinh_Nghe_An_Province.html",
      "reviews": 31,
      "rating": 3.5,
      "price_range_usd": "$$ - $$$",
      "is_sponsored": false,
      "menu_link": null,
      "reservation_link": null,
      "featured_image": "https://dynamic-media-cdn.tripadvisor.com/media/photo-o/05/63/ab/10/at-miaow-pizza.jpg",
      "latitude": 18.678047,
      "longitude": 105.67822,
      "has_delivery": false,
      "is_premium": false,
      "cuisines": [
        "Italian",
        "Pizza"
      ]
    },
    {
      "id": 17464894,
      "name": "Nha Hang Cuong Hang 129",
      "link": "https://www.tripadvisor.com/Restaurant_Review-g4235728-d17464894-Reviews-Nha_Hang_Cuong_Hang_129-Cua_Lo_Nghe_An_Province.html",
      "reviews": 1,
      "rating": 1,
      "price_range_usd": "$",
      "is_sponsored": false,
      "menu_link": null,
      "reservation_link": null,
      "featured_image": "https://dynamic-media-cdn.tripadvisor.com/media/photo-o/17/8a/9c/9b/getlstd-property-photo.jpg",
      "latitude": 18.804188,
      "longitude": 105.72648,
      "has_delivery": false,
      "is_premium": false,
      "cuisines": [
        "Seafood",
        "Deli"
      ]
    },
    {
      "id": 23016501,
      "name": "D'Art Chocolate Vinh - Nghệ An",
      "link": "https://www.tripadvisor.com/Restaurant_Review-g1554764-d23016501-Reviews-D_Art_Chocolate_Vinh_Ngh_An-Vinh_Nghe_An_Province.html",
      "reviews": 6,
      "rating": 5,
      "price_range_usd": "$$ - $$$",
      "is_sponsored": false,
      "menu_link": "https://socolatpvinhna.blogspot.com",
      "reservation_link": null,
      "featured_image": "https://dynamic-media-cdn.tripadvisor.com/media/photo-o/1c/76/c4/f0/h-p-socola.jpg",
      "latitude": 18.679382,
      "longitude": 105.69968,
      "has_delivery": false,
      "is_premium": false,
      "cuisines": [
        "Belgian",
        "European",
        "Deli",
        "Healthy"
      ]
    },
    {
      "id": 4758191,
      "name": "Viet Duc",
      "link": "https://www.tripadvisor.com/Restaurant_Review-g1554764-d4758191-Reviews-Viet_Duc-Vinh_Nghe_An_Province.html",
      "reviews": 5,
      "rating": 4.4,
      "price_range_usd": null,
      "is_sponsored": false,
      "menu_link": null,
      "reservation_link": null,
      "featured_image": "https://dynamic-media-cdn.tripadvisor.com/media/photo-o/1a/f2/8c/49/c-m-giac-m-cung-ben-gia.jpg",
      "latitude": 18.68043,
      "longitude": 105.70403,
      "has_delivery": false,
      "is_premium": false,
      "cuisines": [
        "Vietnamese"
      ]
    },
    {
      "id": 24110782,
      "name": "Nhà Hàng Kinh Vĩ Brasserie",
      "link": "https://www.tripadvisor.com/Restaurant_Review-g1554764-d24110782-Reviews-Nha_Hang_Kinh_Vi_Brasserie-Vinh_Nghe_An_Province.html",
      "reviews": 1,
      "rating": 5,
      "price_range_usd": null,
      "is_sponsored": false,
      "menu_link": null,
      "reservation_link": null,
      "featured_image": "https://dynamic-media-cdn.tripadvisor.com/media/photo-o/25/0b/25/85/nha-hang-kinh-vi.jpg",
      "latitude": 18.686428,
      "longitude": 105.68687,
      "has_delivery": false,
      "is_premium": false,
      "cuisines": [
        "Cafe",
        "Deli"
      ]
    },
    {
      "id": 7070092,
      "name": "Vuvuzela",
      "link": "https://www.tripadvisor.com/Restaurant_Review-g1554764-d7070092-Reviews-Vuvuzela-Vinh_Nghe_An_Province.html",
      "reviews": 36,
      "rating": 3.5,
      "price_range_usd": "$$ - $$$",
      "is_sponsored": false,
      "menu_link": null,
      "reservation_link": null,
      "featured_image": "https://dynamic-media-cdn.tripadvisor.com/media/photo-o/12/be/e3/34/photo9jpg.jpg",
      "latitude": 18.675035,
      "longitude": 105.67438,
      "has_delivery": false,
      "is_premium": false,
      "cuisines": [
        "Brew Pub",
        "Bar",
        "Pub"
      ]
    },
    {
      "id": 10865599,
      "name": "Nhà Hàng Hoàng An Villa",
      "link": "https://www.tripadvisor.com/Restaurant_Review-g1554764-d10865599-Reviews-Nha_Hang_Hoang_An_Villa-Vinh_Nghe_An_Province.html",
      "reviews": 1,
      "rating": 5,
      "price_range_usd": null,
      "is_sponsored": false,
      "menu_link": null,
      "reservation_link": null,
      "featured_image": "https://dynamic-media-cdn.tripadvisor.com/media/photo-o/13/8a/a9/fb/photo1jpg.jpg",
      "latitude": 18.66587,
      "longitude": 105.67198,
      "has_delivery": false,
      "is_premium": false,
      "cuisines": [
        "Seafood",
        "Thai",
        "Vietnamese",
        "Diner"
      ]
    },
    {
      "id": 13124568,
      "name": "Bachi Bachi Restaurant",
      "link": "https://www.tripadvisor.com/Restaurant_Review-g1554764-d13124568-Reviews-Bachi_Bachi_Restaurant-Vinh_Nghe_An_Province.html",
      "reviews": 5,
      "rating": 5,
      "price_range_usd": "$",
      "is_sponsored": false,
      "menu_link": null,
      "reservation_link": null,
      "featured_image": "https://dynamic-media-cdn.tripadvisor.com/media/photo-o/11/40/2b/02/1510484805558-largejpg.jpg",
      "latitude": 18.671791,
      "longitude": 105.69926,
      "has_delivery": false,
      "is_premium": false,
      "cuisines": [
        "Asian",
        "Korean"
      ]
    },
    {
      "id": 27782824,
      "name": "Nhà Hàng Gió Biển - 252 Bình Minh, Cửa Lò",
      "link": "https://www.tripadvisor.com/Restaurant_Review-g4235728-d27782824-Reviews-Nha_Hang_Gio_Bi_n_252_Binh_Minh_C_a_Lo-Cua_Lo_Nghe_An_Province.html",
      "reviews": 0,
      "rating": 0,
      "price_range_usd": null,
      "is_sponsored": false,
      "menu_link": null,
      "reservation_link": null,
      "featured_image": null,
      "latitude": 10.7692,
      "longitude": 106.60293,
      "has_delivery": false,
      "is_premium": false,
      "cuisines": [
        "Seafood",
        "Vietnamese",
        "Beer restaurants"
      ]
    },
    {
      "id": 33107922,
      "name": "Nathan Thai Fusion Restaurant",
      "link": "https://www.tripadvisor.com/Restaurant_Review-g1554764-d33107922-Reviews-Nathan_Thai_Fusion_Restaurant-Vinh_Nghe_An_Province.html",
      "reviews": 0,
      "rating": 0,
      "price_range_usd": "$$ - $$$",
      "is_sponsored": false,
      "menu_link": "https://online.fliphtml5.com/ddugp/fkuo/",
      "reservation_link": null,
      "featured_image": "https://dynamic-media-cdn.tripadvisor.com/media/photo-o/2f/c8/63/bd/nathan-thai-contemporary.jpg",
      "latitude": 18.672012,
      "longitude": 105.6985,
      "has_delivery": false,
      "is_premium": false,
      "cuisines": [
        "Thai"
      ]
    },
    {
      "id": 12882086,
      "name": "nha hang du thuyen Hai Chau",
      "link": "https://www.tripadvisor.com/Restaurant_Review-g1554764-d12882086-Reviews-Nha_hang_du_thuyen_Hai_Chau-Vinh_Nghe_An_Province.html",
      "reviews": 1,
      "rating": 4,
      "price_range_usd": null,
      "is_sponsored": false,
      "menu_link": null,
      "reservation_link": null,
      "featured_image": "https://dynamic-media-cdn.tripadvisor.com/media/photo-o/10/a6/69/19/nha-hang-du-thuy-n-h.jpg",
      "latitude": 18.644093,
      "longitude": 105.69959,
      "has_delivery": false,
      "is_premium": false,
      "cuisines": [
        "Seafood",
        "Vietnamese"
      ]
    },
    {
      "id": 18114302,
      "name": "Fujimo Restaurant",
      "link": "https://www.tripadvisor.com/Restaurant_Review-g1554764-d18114302-Reviews-Fujimo_Restaurant-Vinh_Nghe_An_Province.html",
      "reviews": 1,
      "rating": 5,
      "price_range_usd": null,
      "is_sponsored": false,
      "menu_link": null,
      "reservation_link": null,
      "featured_image": "https://dynamic-media-cdn.tripadvisor.com/media/photo-o/18/b6/88/db/fujimo-restaurant-add.jpg",
      "latitude": null,
      "longitude": null,
      "has_delivery": false,
      "is_premium": false,
      "cuisines": []
    }
  ]
}